README.rst
setup.py
multilogger_collectd/__init__.py
multilogger_collectd/multilogger.py
multilogger_collectd/multilogger_collectd.py
multilogger_collectd.egg-info/PKG-INFO
multilogger_collectd.egg-info/SOURCES.txt
multilogger_collectd.egg-info/dependency_links.txt
multilogger_collectd.egg-info/requires.txt
multilogger_collectd.egg-info/top_level.txt