Metadata-Version: 1.1
Name: multilogger-collectd
Version: 0.1.1
Summary: A collectd plugin for monitoring AREXX Multiloggers
Home-page: https://github.com/pka/arexx-multilogger-collectd-plugin
Author: Pirmin Kalberer
Author-email: pka@sourcepole.ch
License: GPLv2
Keywords: AREXX multilogger collectd
Platform: UNKNOWN
Classifier: Development Status :: 4 - Beta
Classifier: Environment :: Console
Classifier: Intended Audience :: System Administrators
Classifier: License :: OSI Approved :: GNU General Public License v2 (GPLv2)
Classifier: Natural Language :: English
Classifier: Operating System :: POSIX
Classifier: Programming Language :: Python
Classifier: Topic :: System :: Monitoring
